Metadata-Version: 1.0
Name: pysatml
Version: 0.1.1
Summary: Satellite data imagery preprocessing and formatting functionality for typical machine learning/computer vision tasks.
Home-page: https://github.com/adrianalbert/pysatml
Author: Adrian Albert
Author-email: adrian.t.albert@gmail.com
License: MIT
Platform: UNKNOWN
